Workbook

Sheet Read me
A1: Dream OS Capability Map
A2: Competitive capability map, researched 31 August 2026
A4: What this is
A5: 122 estate-agency capabilities, and whether each of the four systems worth learning from does it.
A6: The four columns were checked against vendor documentation and help centres, not affiliate review sites.
A8: The four systems
A9: BoldTrail — US, formerly kvCORE, ~400,000 agents. The famous one: lead conversion, IDX, dialer, AI, back office.
A10: Reapit — UK, 15,000 branches. The incumbent, and the platform architecture is the lesson.
A11: Street.co.uk — UK challenger. The best modern execution of the whole agency workflow.
A12: Entegral Base — SA, R949/month for up to 50 users. What Bronwyn could buy tomorrow, so it is the price ceiling.
A14: How to use it
A15: Column K, Decision, is a dropdown: Must have / Nice to have / Not for us. Pick one per row.
... A29: A practitioner may not accept a mandate without a signed mandatory disclosure form, annexed to the sale. If it is missing, the agreement reads as though no defects were disclosed. (Row M11)

Sheet Capability map
A1: ID | B1: Area | C1: Capability | D1: Why it matters | E1: BoldTrail | F1: Reapit | G1: Street.co.uk | H1: Entegral Base | I1: Dream OS today | J1: Dream OS note | K1: Decision | L1: Note
A2: C01 | B2: Contacts & leads | C2: Contact record with multiple roles | D2: One person who is a seller here and a buyer there, without duplicate records | E2: Yes | F2: Yes | G2: Yes | H2: Yes | I2: Built | J2: party table + role timeline on /contacts
A3: C02 | B3: Contacts & leads | C3: Buyer requirement profile | D3: Area, price band, beds, must-haves — stored, not in the agent's head | E3: Yes | F3: Yes | G3: Yes | H3: Yes | I3: Planned | J3: party_interest in migration 0066, no UI
A4: C03 | B4: Contacts & leads | C4: Buyer-to-listing matching | D4: Show me everything on our books this buyer should see | E4: Yes | F4: Yes | G4: Yes | H4: Yes | I4: Not yet
A5: C04 | B5: Contacts & leads | C5: Reverse matching on new stock | D5: New listing lands, system names the buyers to ring first | E5: Partial | F5: Yes | G5: Yes | H5: Yes | I5: Not yet
A6: C05 | B6: Contacts & leads | C6: Portal enquiry straight into the CRM | D6: P24 / Private Property leads arrive as records, not inbox clutter | E6: Yes | F6: Yes | G6: Yes | H6: Yes | I6: Partial | J6: email intake parses enquiries; no portal feed
A7: C06 | B7: Contacts & leads | C7: Lead source attribution | D7: Which portal, campaign or board brought this buyer | E7: Yes | F7: Partial | G7: Yes | H7: Yes | I7: Planned | J7: contact_source enum, unwired
A8: C07 | B8: Contacts & leads | C8: Automatic lead routing | D8: Round-robin, by suburb, by price band — assigned without a human | E8: Yes | F8: Partial | G8: Yes | H8: Partial | I8: Not yet
A9: C08 | B9: Contacts & leads | C9: Lead scoring | D9: Rank who is actually close to transacting | E9: Yes | F9: Not confirmed | G9: Partial | H9: No | I9: Not yet
A10: C09 | B10: Contacts & leads | C10: Duplicate detection & merge | D10: The same seller entered three ways, caught before it spreads | E10: Partial | F10: Partial | G10: Partial | H10: Not confirmed | I10: Built | J10: match_candidate dedup pipeline
A11: C10 | B11: Contacts & leads | C11: Full interaction timeline | D11: Every call, mail, viewing and document on one record | E11: Yes | F11: Yes | G11: Yes | H11: Yes | I11: Built
A12: L01 | B12: Listings & property data | C12: Listing record with status pipeline | D12: Preparing → listed → under offer → sold, as states not labels | E12: Yes | F12: Yes | G12: Yes | H12: Yes | I12: Built
A13: L02 | B13: Listings & property data | C13: Freehold vs sectional title as structure | D13: Drives which clearance certificate and which third party — not a tag | E13: No | F13: Partial | G13: Partial | H13: Partial | I13: Built | J13: ownership_type × property_type seeded
A14: L03 | B14: Listings & property data | C14: Erf / cadastral parcel data | D14: The stand itself as a record, with its diagram and boundaries | E14: No | F14: No | G14: No | H14: No | I14: Built | J14: cadastral_parcel + erf, /erf-lookup, tile server
A15: L04 | B15: Listings & property data | C15: Map with cadastral polygons | D15: Shaded erven, not pins floating on a basemap | E15: Partial | F15: Partial | G15: Partial | H15: Partial | I15: Built | J15: MapView.tsx, plan 005 shipped
A16: L05 | B16: Listings & property data | C16: Municipal valuation roll | D16: What the municipality thinks it's worth, next to what we're asking | E16: No | F16: No | G16: No | H16: No | I16: Built | J16: muni_valuation + upload/parse/apply
A17: L06 | B17: Listings & property data | C17: Deeds / title enrichment | D17: Registered owner, purchase date and price pulled automatically | E17: Partial | F17: Partial | G17: Partial | H17: Partial | I17: Built | J17: Lightstone, budget-capped
A18: L07 | B18: Listings & property data | C18: Competitor stock ingest | D18: Everything on the market in Knysna, not only our own mandates | E18: Partial | F18: No | G18: No | H18: No | I18: Built | J18: P24 scraper; geocoding still unreliable
A19: L08 | B19: Listings & property data | C19: Photo & media library | D19: Ordered, captioned, reusable across marketing | E19: Yes | F19: Yes | G19: Yes | H19: Yes | I19: Built | J19: media bucket + lightbox
A20: L09 | B20: Listings & property data | C20: Floorplans | D20: Drawn or uploaded, shown on the listing | E20: Yes | F20: Yes | G20: Yes | H20: Not confirmed | I20: Not yet
A21: L10 | B21: Listings & property data | C21: Virtual tours & video | D21: 360° or walkthrough attached to the listing | E21: Yes | F21: Partial | G21: Yes | H21: Yes | I21: Not yet
A22: L11 | B22: Listings & property data | C22: Brochure & window card generation | D22: Branded PDF off the listing data, no designer in the loop | E22: Yes | F22: Yes | G22: Yes | H22: Yes | I22: Not yet
A23: L12 | B23: Listings & property data | C23: Price history | D23: Every reduction, dated, for the CMA conversation | E23: Yes | F23: Yes | G23: Yes | H23: Partial | I23: Built | J23: listing_price_history
A24: M01 | B24: Mandates | C24: Mandate as a first-class record | D24: The instruction to market, not just a listing with a date on it | E24: No | F24: Yes | G24: Yes | H24: Partial | I24: Built | J24: mandate table + /mandates
A25: M02 | B25: Mandates | C25: Mandate types modelled properly | D25: Sole, open, joint, multi-listing — each with its own rules | E25: No | F25: Yes | G25: Yes | H25: Not confirmed | I25: Partial | J25: sole and exclusive are two enum values for one thing — consolidate
A26: M03 | B26: Mandates | C26: Expiry tracking with auto-expire | D26: Lapsed mandates stop counting as live stock on their own | E26: No | F26: Yes | G26: Yes | H26: Yes | I26: Built | J26: threshold watchlist on /mandates
A27: M04 | B27: Mandates | C27: Renewal reminders before expiry | D27: Prompted to re-sign in time, not after the seller has gone | E27: No | F27: Yes | G27: Yes | H27: Yes | I27: Built | J27: mandate.expiry_window_days setting
A28: M05 | B28: Mandates | C28: Mandate generated from a template | D28: The real master document, filled from the record | E28: Partial | F28: Partial | G28: Partial | H28: No | I28: Partial | J28: MandateSole.tsx built from the wrong master — replace wholesale
A29: M06 | B29: Mandates | C29: Clause library with variants | D29: One clause, several approved wordings, chosen per deal | E29: No | F29: No | G29: No | H29: No | I29: Planned | J29: 0065_document_engine.sql written, not applied
A30: M07 | B30: Mandates | C30: E-signature on the mandate | D30: Signed on Bronwyn's iPad at the kitchen table | E30: Yes | F30: Partial | G30: Partial | H30: No | I30: Not yet
A31: M08 | B31: Mandates | C31: Signed mandate stored and findable | D31: "What did we send the Wilsons in March" has an answer | E31: Yes | F31: Yes | G31: Yes | H31: Partial | I31: Not yet | J31: generated mandates write no document row today
A32: M09 | B32: Mandates | C32: Joint-mandate counterparty agency | D32: Pam Golding on the other side, and the split that follows | E32: No | F32: Yes | G32: Partial | H32: Not confirmed | I32: Built | J32: agency table exists for exactly this
A33: M10 | B33: Mandates | C33: CPA duration & notice rules enforced | D33: 24-month cap, 20-day cancellation, pre-expiry notice — in the software | E33: No | F33: No | G33: No | H33: No | I33: Not yet | J33: nobody does this; verify sections before coding
A34: M11 | B34: Mandates | C34: Mandatory disclosure form | D34: Signed by the seller before we take the mandate, annexed to the sale | E34: No | F34: No | G34: Partial | H34: No | I34: Not yet | J34: no signed form, no valid mandate — and the agreement then reads as defect-free
A35: V01 | B35: Viewings & vendor care | C35: Viewing scheduling | D35: Diary of who sees what, when, with which agent | E35: Partial | F35: Yes | G35: Yes | H35: Partial | I35: Built | J35: viewing table + weekly /viewings calendar
A36: V02 | B36: Viewings & vendor care | C36: Buyer books their own viewing | D36: Self-service slots, 24/7, no phone tag | E36: Partial | F36: Partial | G36: Yes | H36: No | I36: Not yet
A37: V03 | B37: Viewings & vendor care | C37: Show day management | D37: Open house with attendee capture, walk-ins included | E37: Yes | F37: Yes | G37: Yes | H37: Partial | I37: Built | J37: walk-in names captured without a party record
A38: V04 | B38: Viewings & vendor care | C38: Structured viewing feedback | D38: Interested / not / why — as data, not a note | E38: No | F38: Yes | G38: Yes | H38: Partial | I38: Built | J38: viewing_attendee.is_interested tri-state
A39: V05 | B39: Viewings & vendor care | C39: Automated feedback request | D39: The buyer gets asked without anyone remembering to ask | E39: Partial | F39: Partial | G39: Yes | H39: No | I39: Not yet
A40: V06 | B40: Viewings & vendor care | C40: Vendor progress report | D40: Weekly "here's what happened on your house" going out automatically | E40: No | F40: Yes | G40: Yes | H40: Yes | I40: Not yet | J40: the single cheapest seller-retention feature on this sheet
A41: V07 | B41: Viewings & vendor care | C41: Seller portal | D41: The seller logs in and sees views, feedback, offers | E41: No | F41: Partial | G41: Yes | H41: No | I41: Not yet | J41: client role reserved in RLS, not enabled
A42: V08 | B42: Viewings & vendor care | C42: Buyer portal | D42: Saved properties, documents, where their offer stands | E42: Yes | F42: Partial | G42: Yes | H42: Partial | I42: Not yet
A43: V09 | B43: Viewings & vendor care | C43: Valuation / CMA pipeline | D43: Appraisal booked → presented → won or lost, tracked as a funnel | E43: Yes | F43: Yes | G43: Yes | H43: Partial | I43: Partial | J43: Lightstone + muni data exist; no appraisal funnel
A44: D01 | B44: Offers & deal progression | C44: Deal pipeline through to registration | D44: One board from mandate to transfer, not a spreadsheet | E44: Yes | F44: Yes | G44: Yes | H44: Yes | I44: Built | J44: transfer table + /pipeline
A45: D02 | B45: Offers & deal progression | C45: Structured offer record | D45: Amount, occupation date, expiry — fields, not a PDF | E45: Partial | F45: Yes | G45: Yes | H45: No | I45: Built | J45: offer table extended in 0057
A46: D03 | B46: Offers & deal progression | C46: Agreement of Sale is the offer | D46: No separate OTP at Dream — one irrevocable document | E46: No | F46: No | G46: No | H46: No | I46: Built | J46: domain correction already in the model
A47: D04 | B47: Offers & deal progression | C47: Suspensive conditions with dates | D47: Bond by the 30th, sale of buyer's house — each with its own state | E47: Partial | F47: Partial | G47: Partial | H47: No | I47: Built | J47: suspensive_condition + evidence document link
A48: D05 | B48: Offers & deal progression | C48: Automatic lapse when a condition fails | D48: The agreement is void, and the system knows it that morning | E48: No | F48: No | G48: No | H48: No | I48: Partial | J48: lifecycle exists; automatic lapse does not
A49: D06 | B49: Offers & deal progression | C49: Bond application tracking | D49: Which bank, applied when, approved for how much | E49: Partial | F49: Partial | G49: Partial | H49: No | I49: Partial | J49: offer.bond_* fields only, no workflow
A50: D07 | B50: Offers & deal progression | C50: Conveyancer assignment & handoff | D50: Attorney on the deal, with the pack sent to them | E50: Partial | F50: Yes | G50: Yes | H50: No | I50: Not yet | J50: conveyancer tables exist; no UI assigns one
A51: D08 | B51: Offers & deal progression | C51: Transfer & registration progress | D51: Lodged, examined, registered — visible without phoning the attorney | E51: No | F51: Partial | G51: Partial | H51: No | I51: Built | J51: transfer.registered_date + RegisteredStamp
A52: D09 | B52: Offers & deal progression | C52: Rates clearance step | D52: Municipal clearance as a blocking task with a 60-day clock | E52: No | F52: No | G52: No | H52: No | I52: Not yet | J52: freehold deals cannot register without it
A53: D10 | B53: Offers & deal progression | C53: Levy clearance step | D53: Body corporate clearance — slower, and a different party entirely | E53: No | F53: No | G53: No | H53: No | I53: Not yet | J53: sectional title only; drives off L02
A54: D11 | B54: Offers & deal progression | C54: Chain / dependent deals | D54: Their sale funds this purchase — see the whole chain | E54: No | F54: Yes | G54: Yes | H54: No | I54: Not yet | J54: the UK's core idea; partly relevant here
A55: D12 | B55: Offers & deal progression | C55: Milestone comms to all parties | D55: Bond approved → everyone told, without anyone typing it | E55: Yes | F55: Partial | G55: Yes | H55: Partial | I55: Not yet
A56: $01 | B56: Money — commission & trust | C56: Commission calculated from the deal | D56: Gross, VAT, net — off the sale price automatically | E56: Yes | F56: Yes | G56: Partial | H56: Yes | I56: Not yet | J56: commission table exists; no code reads or writes it
A57: $02 | B57: Money — commission & trust | C57: Splits between agents and agencies | D57: Listing agent, selling agent, joint-mandate partner | E57: Yes | F57: Yes | G57: Partial | H57: Yes | I57: Not yet
A58: $03 | B58: Money — commission & trust | C58: Agent commission statements | D58: A slip each agent can check against their own numbers | E58: Yes | F58: Yes | G58: Partial | H58: Yes | I58: Not yet
A59: $04 | B59: Money — commission & trust | C59: FFC gate on payout | D59: No valid Fidelity Fund Certificate, no commission — enforced | E59: No | F59: No | G59: No | H59: No | I59: Not yet | J59: FFC dates are tracked; nothing blocks on them yet
A60: $05 | B60: Money — commission & trust | C60: Commission forecast | D60: What the pipeline is worth if it all registers | E60: Yes | F60: Yes | G60: Yes | H60: Yes | I60: Not yet
A61: $06 | B61: Money — commission & trust | C61: Trust account ledger | D61: Client money in, held, disbursed — with provenance per deposit | E61: No | F61: Yes | G61: Yes | H61: No | I61: Not yet | J61: s54 requires the account; the OS doesn't see it
A62: $07 | B62: Money — commission & trust | C62: Trust reconciliation & audit export | D62: Monthly recon the auditor accepts without a rebuild | E62: No | F62: Yes | G62: Yes | H62: No | I62: Not yet
A63: $08 | B63: Money — commission & trust | C63: Accounting integration | D63: Xero or Sage, so the books aren't retyped | E63: Yes | F63: Partial | G63: Partial | H63: Partial | I63: Not yet
A64: $09 | B64: Money — commission & trust | C64: Referral & bond origination income | D64: The fee from the originator, tracked like any other income | E64: Partial | F64: Partial | G64: Partial | H64: Partial | I64: Not yet
A65: P01 | B65: Documents & signature | C65: Document storage with access control | D65: Right people, right documents, signed URLs that expire | E65: Yes | F65: Yes | G65: Yes | H65: Yes | I65: Partial | J65: 3 private buckets; /documents route 404s
A66: P02 | B66: Documents & signature | C66: Template-driven generation | D66: Thirteen masters, filled from the record, correct every time | E66: Partial | F66: Yes | G66: Partial | H66: Partial | I66: Planned | J66: plan 007 — templates arrived 2026-08-04
A67: P03 | B67: Documents & signature | C67: Versioned drafts | D67: Draft, revised, final — with who changed what | E67: Partial | F67: Partial | G67: Partial | H67: No | I67: Planned | J67: document_draft in 0065
A68: P04 | B68: Documents & signature | C68: E-signature | D68: Signed remotely, legally, without a scanner | E68: Yes | F68: Partial | G68: Partial | H68: No | I68: Not yet
A69: P05 | B69: Documents & signature | C69: Signed-document register per deal | D69: Everything executed on this transaction, in one place | E69: Yes | F69: Yes | G69: Yes | H69: Partial | I69: Not yet
A70: P06 | B70: Documents & signature | C70: Document expiry tracking | D70: Certificates, FFCs, mandates — all with a clock on them | E70: Partial | F70: Yes | G70: Yes | H70: Partial | I70: Partial | J70: FFC and mandate only
A71: P07 | B71: Documents & signature | C71: Audit trail on every change | D71: Field-level before and after, with the user's name | E71: Partial | F71: Yes | G71: Yes | H71: Yes | I71: Partial | J71: audit_log written from one file only
A72: P08 | B72: Documents & signature | C72: Separate compliance store | D72: FICA documents walled off from general files | E72: No | F72: Partial | G72: Partial | H72: Partial | I72: Built | J72: admin-only fica bucket
A73: F01 | B73: Compliance — FICA, POPIA, PPRA | C73: FICA / KYC capture | D73: ID, proof of address, source of funds, on the file | E73: No | F73: Yes | G73: Yes | H73: Yes | I73: Built | J73: fica table + status badge + gap tracking
A74: F02 | B74: Compliance — FICA, POPIA, PPRA | C74: Live ID, PEP & sanctions screening | D74: Verified against a real source, not eyeballed | E74: No | F74: Yes | G74: Yes | H74: Yes | I74: Not yet | J74: Entegral Vault: R14.99 an ID check, pay-as-you-go
A75: F03 | B75: Compliance — FICA, POPIA, PPRA | C75: Risk rating per client | D75: The RMCP's risk categories applied automatically | E75: No | F75: Partial | G75: Yes | H75: Yes | I75: Not yet
A76: F04 | B76: Compliance — FICA, POPIA, PPRA | C76: FICA gaps against live deals | D76: Which running transactions are missing paperwork, today | E76: No | F76: Partial | G76: Partial | H76: Partial | I76: Built | J76: /compliance
A77: F05 | B77: Compliance — FICA, POPIA, PPRA | C77: POPIA consent capture | D77: Recorded consent, per purpose, per contact | E77: Partial | F77: Partial | G77: Partial | H77: No | I77: Planned | J77: consent table since 0004 — nothing has ever written to it
A78: F06 | B78: Compliance — FICA, POPIA, PPRA | C78: Consent-aware suppression | D78: Nobody gets marketed to who said no | E78: Partial | F78: Partial | G78: Partial | H78: No | I78: Planned | J78: contact_point_suppression, unwired
A79: F07 | B79: Compliance — FICA, POPIA, PPRA | C79: FFC on the practitioner record | D79: Number and expiry against each agent | E79: No | F79: No | G79: No | H79: No | I79: Built | J79: 0051_agent_ffc_expiry — nobody else has this
A80: F08 | B80: Compliance — FICA, POPIA, PPRA | C80: FFC expiry watchlist | D80: Warned before an agent becomes uncommissionable | E80: No | F80: No | G80: No | H80: No | I80: Built
A81: F09 | B81: Compliance — FICA, POPIA, PPRA | C81: Data residency in a chosen region | D81: Where the personal data physically sits | E81: No | F81: Partial | G81: Partial | H81: Not confirmed | I81: Built | J81: Supabase EU/Ireland, POPIA-motivated
A82: K01 | B82: Communication | C82: Send email from the record | D82: Correspondence that lands back on the contact | E82: Yes | F82: Partial | G82: Yes | H82: Partial | I82: Not yet | J82: outbound is admin alerts only
A83: K02 | B83: Communication | C83: Inbound email parsed into records | D83: Enquiries become contacts without retyping | E83: Yes | F83: Partial | G83: Yes | H83: Yes | I83: Built | J83: Resend + LLM extraction, /inbox
A84: K03 | B84: Communication | C84: SMS from the record | D84: Two-way, threaded on the contact | E84: Yes | F84: No | G84: Partial | H84: Yes | I84: Not yet
A85: K04 | B85: Communication | C85: WhatsApp from the record | D85: How South Africans actually transact | E85: No | F85: No | G85: Yes | H85: Yes | I85: Not yet | J85: party.whatsapp is a field; no messaging
A86: K05 | B86: Communication | C86: Templates with merge fields | D86: Same message, right name, every time | E86: Yes | F86: Yes | G86: Yes | H86: Yes | I86: Not yet
A87: K06 | B87: Communication | C87: Bulk / campaign send | D87: New listing to the matched buyer list in one action | E87: Yes | F87: Yes | G87: Yes | H87: No | I87: Planned | J87: campaign tables exist; gated on NCC registration
A88: K07 | B88: Communication | C88: Drip & nurture sequences | D88: The 18-month seller who needs touching six times | E88: Yes | F88: Partial | G88: Yes | H88: No | I88: Not yet
A89: K08 | B89: Communication | C89: Call logging / dialer | D89: Calls on the record without writing them up | E89: Yes | F89: Partial | G89: Yes | H89: No | I89: Not yet
A90: K09 | B90: Communication | C90: Open & click tracking | D90: Who actually read the mailer | E90: Yes | F90: Partial | G90: Partial | H90: No | I90: Not yet
A91: K10 | B91: Communication | C91: Task & reminder engine | D91: Follow-ups that chase you, not the other way round | E91: Yes | F91: Yes | G91: Yes | H91: Yes | I91: Partial | J91: watchlists only, no general task engine
A92: W01 | B92: Marketing, portals & web presence | C92: Push listings to Property24 | D92: Our stock, out to the dominant SA portal, automatically | E92: No | F92: No | G92: No | H92: Yes | I92: Not yet | J92: we scrape P24 in; we publish nothing out
A93: W02 | B93: Marketing, portals & web presence | C93: Push listings to Private Property | D93: Second portal, same feed | E93: No | F93: No | G93: No | H93: Yes | I93: Not yet
A94: W03 | B94: Marketing, portals & web presence | C94: Free portal syndication | D94: MyProperty and friends, at no marketing cost | E94: No | F94: No | G94: No | H94: Yes | I94: Not yet | J94: Entegral Sync reaches 18 destinations from R219/50 listings
A95: W04 | B95: Marketing, portals & web presence | C95: Feed API others can consume | D95: Publish once, let anyone pull it | E95: No | F95: Partial | G95: Partial | H95: Yes | I95: Not yet | J95: 2023 Competition Commission ruling forces free interop
A96: W05 | B96: Marketing, portals & web presence | C96: Agency website fed from the CRM | D96: dreamknysna.co.za updates itself when a listing changes | E96: Yes | F96: Partial | G96: Partial | H96: Yes | I96: Not yet | J96: no public route exists; middleware gates everything
A97: W06 | B97: Marketing, portals & web presence | C97: Public listing pages & SEO | D97: A page per property that Google can find | E97: Yes | F97: Partial | G97: Partial | H97: Yes | I97: Not yet
A98: W07 | B98: Marketing, portals & web presence | C98: Social auto-posting & paid ads | D98: Facebook and Instagram campaigns off the listing | E98: Yes | F98: Partial | G98: Partial | H98: Yes | I98: Not yet | J98: Flow does exactly this locally, as a layer
A99: W08 | B99: Marketing, portals & web presence | C99: Saved searches & buyer alerts | D99: Buyers hear about matching stock before the portal shows it | E99: Yes | F99: Yes | G99: Yes | H99: Yes | I99: Not yet
A100: W09 | B100: Marketing, portals & web presence | C100: Landing pages for lead capture | D100: Valuation and area pages that collect names | E100: Yes | F100: Partial | G100: Partial | H100: Partial | I100: Not yet
...

Sheet Summary
A1: Where the decisions stand
A2: These cells are formulas. They update as you fill in column K of the map.
A4: Decision | B4: Rows
A5: Must have | B5: =COUNTIF('Capability map'!$K$2:$K$123,A5) -> 0
A6: Nice to have | B6: =COUNTIF('Capability map'!$K$2:$K$123,A6) -> 0
A7: Not for us | B7: =COUNTIF('Capability map'!$K$2:$K$123,A7) -> 0
A8: Still undecided | B8: =COUNTBLANK('Capability map'!$K$2:$K$123) -> 122
A9: Total capabilities | B9: =COUNTA('Capability map'!$A$2:$A$123) -> 122
A11: By area
A12: Area | B12: Rows | C12: Must have | D12: Dream OS built | E12: Dream OS not yet
A13: Contacts & leads | B13: =COUNTIF('Capability map'!$B$2:$B$123,$A13) -> 10 | C13: =COUNTIFS('Capability map'!$B$2:$B$123,$A13,'Capability map'!$K$2:$K$123,"Must have") -> 0 | D13: =COUNTIFS('Capability map'!$B$2:$B$123,$A13,'Capability map'!$I$2:$I$123,"Built") -> 3 | E13: =COUNTIFS('Capability map'!$B$2:$B$123,$A13,'Capability map'!$I$2:$I$123,"Not yet") -> 4
A14: Listings & property data | B14: =COUNTIF('Capability map'!$B$2:$B$123,$A14) -> 12 | C14: =COUNTIFS('Capability map'!$B$2:$B$123,$A14,'Capability map'!$K$2:$K$123,"Must have") -> 0 | D14: =COUNTIFS('Capability map'!$B$2:$B$123,$A14,'Capability map'!$I$2:$I$123,"Built") -> 9 | E14: =COUNTIFS('Capability map'!$B$2:$B$123,$A14,'Capability map'!$I$2:$I$123,"Not yet") -> 3
A15: Mandates | B15: =COUNTIF('Capability map'!$B$2:$B$123,$A15) -> 11 | C15: =COUNTIFS('Capability map'!$B$2:$B$123,$A15,'Capability map'!$K$2:$K$123,"Must have") -> 0 | D15: =COUNTIFS('Capability map'!$B$2:$B$123,$A15,'Capability map'!$I$2:$I$123,"Built") -> 4 | E15: =COUNTIFS('Capability map'!$B$2:$B$123,$A15,'Capability map'!$I$2:$I$123,"Not yet") -> 4
A16: Viewings & vendor care | B16: =COUNTIF('Capability map'!$B$2:$B$123,$A16) -> 9 | C16: =COUNTIFS('Capability map'!$B$2:$B$123,$A16,'Capability map'!$K$2:$K$123,"Must have") -> 0 | D16: =COUNTIFS('Capability map'!$B$2:$B$123,$A16,'Capability map'!$I$2:$I$123,"Built") -> 3 | E16: =COUNTIFS('Capability map'!$B$2:$B$123,$A16,'Capability map'!$I$2:$I$123,"Not yet") -> 5
A17: Offers & deal progression | B17: =COUNTIF('Capability map'!$B$2:$B$123,$A17) -> 12 | C17: =COUNTIFS('Capability map'!$B$2:$B$123,$A17,'Capability map'!$K$2:$K$123,"Must have") -> 0 | D17: =COUNTIFS('Capability map'!$B$2:$B$123,$A17,'Capability map'!$I$2:$I$123,"Built") -> 5 | E17: =COUNTIFS('Capability map'!$B$2:$B$123,$A17,'Capability map'!$I$2:$I$123,"Not yet") -> 5
A18: Money — commission & trust | B18: =COUNTIF('Capability map'!$B$2:$B$123,$A18) -> 9 | C18: =COUNTIFS('Capability map'!$B$2:$B$123,$A18,'Capability map'!$K$2:$K$123,"Must have") -> 0 | D18: =COUNTIFS('Capability map'!$B$2:$B$123,$A18,'Capability map'!$I$2:$I$123,"Built") -> 0 | E18: =COUNTIFS('Capability map'!$B$2:$B$123,$A18,'Capability map'!$I$2:$I$123,"Not yet") -> 9
A19: Documents & signature | B19: =COUNTIF('Capability map'!$B$2:$B$123,$A19) -> 8 | C19: =COUNTIFS('Capability map'!$B$2:$B$123,$A19,'Capability map'!$K$2:$K$123,"Must have") -> 0 | D19: =COUNTIFS('Capability map'!$B$2:$B$123,$A19,'Capability map'!$I$2:$I$123,"Built") -> 1 | E19: =COUNTIFS('Capability map'!$B$2:$B$123,$A19,'Capability map'!$I$2:$I$123,"Not yet") -> 2
A20: Compliance — FICA, POPIA, PPRA | B20: =COUNTIF('Capability map'!$B$2:$B$123,$A20) -> 9 | C20: =COUNTIFS('Capability map'!$B$2:$B$123,$A20,'Capability map'!$K$2:$K$123,"Must have") -> 0 | D20: =COUNTIFS('Capability map'!$B$2:$B$123,$A20,'Capability map'!$I$2:$I$123,"Built") -> 5 | E20: =COUNTIFS('Capability map'!$B$2:$B$123,$A20,'Capability map'!$I$2:$I$123,"Not yet") -> 2
A21: Communication | B21: =COUNTIF('Capability map'!$B$2:$B$123,$A21) -> 10 | C21: =COUNTIFS('Capability map'!$B$2:$B$123,$A21,'Capability map'!$K$2:$K$123,"Must have") -> 0 | D21: =COUNTIFS('Capability map'!$B$2:$B$123,$A21,'Capability map'!$I$2:$I$123,"Built") -> 1 | E21: =COUNTIFS('Capability map'!$B$2:$B$123,$A21,'Capability map'!$I$2:$I$123,"Not yet") -> 7
A22: Marketing, portals & web presence | B22: =COUNTIF('Capability map'!$B$2:$B$123,$A22) -> 9 | C22: =COUNTIFS('Capability map'!$B$2:$B$123,$A22,'Capability map'!$K$2:$K$123,"Must have") -> 0 | D22: =COUNTIFS('Capability map'!$B$2:$B$123,$A22,'Capability map'!$I$2:$I$123,"Built") -> 0 | E22: =COUNTIFS('Capability map'!$B$2:$B$123,$A22,'Capability map'!$I$2:$I$123,"Not yet") -> 9
A23: AI | B23: =COUNTIF('Capability map'!$B$2:$B$123,$A23) -> 8 | C23: =COUNTIFS('Capability map'!$B$2:$B$123,$A23,'Capability map'!$K$2:$K$123,"Must have") -> 0 | D23: =COUNTIFS('Capability map'!$B$2:$B$123,$A23,'Capability map'!$I$2:$I$123,"Built") -> 1 | E23: =COUNTIFS('Capability map'!$B$2:$B$123,$A23,'Capability map'!$I$2:$I$123,"Not yet") -> 7
A24: Reporting | B24: =COUNTIF('Capability map'!$B$2:$B$123,$A24) -> 7 | C24: =COUNTIFS('Capability map'!$B$2:$B$123,$A24,'Capability map'!$K$2:$K$123,"Must have") -> 0 | D24: =COUNTIFS('Capability map'!$B$2:$B$123,$A24,'Capability map'!$I$2:$I$123,"Built") -> 1 | E24: =COUNTIFS('Capability map'!$B$2:$B$123,$A24,'Capability map'!$I$2:$I$123,"Not yet") -> 6
A25: Platform | B25: =COUNTIF('Capability map'!$B$2:$B$123,$A25) -> 8 | C25: =COUNTIFS('Capability map'!$B$2:$B$123,$A25,'Capability map'!$K$2:$K$123,"Must have") -> 0 | D25: =COUNTIFS('Capability map'!$B$2:$B$123,$A25,'Capability map'!$I$2:$I$123,"Built") -> 1 | E25: =COUNTIFS('Capability map'!$B$2:$B$123,$A25,'Capability map'!$I$2:$I$123,"Not yet") -> 5
A26: Total | B26: =SUM(B13:B25) -> 122 | C26: =SUM(C13:C25) -> 0 | D26: =SUM(D13:D25) -> 34 | E26: =SUM(E13:E25) -> 68
